cs_dlp/__init__.py
cs_dlp/api.py
cs_dlp/commandline.py
cs_dlp/cookies.py
cs_dlp/coursera_dl.py
cs_dlp/credentials.py
cs_dlp/define.py
cs_dlp/downloaders.py
cs_dlp/extractors.py
cs_dlp/filtering.py
cs_dlp/formatting.py
cs_dlp/network.py
cs_dlp/parallel.py
cs_dlp/playlist.py
cs_dlp/utils.py
cs_dlp/workflow.py
cs_dlp-0.12.0b0.dist-info/METADATA
cs_dlp-0.12.0b0.dist-info/WHEEL
cs_dlp-0.12.0b0.dist-info/entry_points.txt
cs_dlp-0.12.0b0.dist-info/licenses/AUTHORS.md
cs_dlp-0.12.0b0.dist-info/licenses/LICENSE
cs_dlp-0.12.0b0.dist-info/RECORD
